{ 
        "drivers":[
        {"driver": {
            "firstName":"Jonh",
            "lastName":"Rambo",
            "dob":"12111988",
            "dobm":"12",
            "dobd":"11",
            "doba":"1988",
            "gender":"M",
            "residenceStatus":"Own"
        }
        }
        ],
        "vehicles":[
        {"vehicle": {
            "year": "2014",
            "make": "BMW",
            "model": "320",
            "subModel": "I SEDAN 4 DOOR"
        }
        },
        {"vehicle": {
            "year": "2010",
            "make": "ACURA",
            "model": "MDX",
            "subModel": "SPORT UTILITY VEHICLE 4 DOOR"
        }
        }
        ],
        "personal": {
            "currentlyInsured" : false,
            "address": "13 Fake Street",
            "email": "qa@vantagemedia.com",
            "phone": "3056464444"
        }
    }